vangogh/__init__.py
vangogh/_version.py
vangogh/cirs_to_gcrs.py
vangogh/heavenly_bodies.py
vangogh/sphere.py
vangogh/data/countries.h5
vangogh/data/earth_day.jpg
vangogh/data/earth_midnight.jpg
vangogh/data/earth_night.jpg
vangogh/data/thats_no_moon.jpg
vangogh/data/thats_no_moon_big.jpg
vangogh/utils/__init__.py
vangogh/utils/package_utils.py
vangogh-0.0.4.dist-info/LICENSE
vangogh-0.0.4.dist-info/METADATA
vangogh-0.0.4.dist-info/WHEEL
vangogh-0.0.4.dist-info/top_level.txt
vangogh-0.0.4.dist-info/RECORD
